multirandom/__init__.py
multirandom/hash_rand/__init__.py
multirandom/hash_rand/original_random.py
multirandom/hash_rand/sha_rand.py
multirandom/true_rand/__init__.py
multirandom/true_rand/rand_using_online_api.py
multirandom/true_rand/rand_via_clicks.py
multirandom/true_rand/weather_rand.py
multirandom/virt_rand/__init__.py
multirandom/virt_rand/flash_rand_and_reverse.py
multirandom/virt_rand/rand_using_virt_lcg.py
multirandom/virt_rand/xor_shift.py
multirandom-0.0.5.dist-info/licenses/LICENSE
multirandom-0.0.5.dist-info/METADATA
multirandom-0.0.5.dist-info/WHEEL
multirandom-0.0.5.dist-info/top_level.txt
multirandom-0.0.5.dist-info/RECORD
