Metadata-Version: 2.4
Name: multirandom
Version: 0.0.5
Summary: 🎲 The truth external PyPI random package, have true_rand, virt_rand, hash_rand, ...
Author-email: BlackCatOfficialytb <quanvm0501@gmail.com>
License-Expression: GPL-3.0-or-later
Project-URL: Homepage, https://github.com/BlackCatOfficialytb/multirandom
Classifier: Programming Language :: Python :: 3.9
Classifier: Operating System :: OS Independent
Requires-Python: >=3.9
License-File: LICENSE
Requires-Dist: aiohttp
Requires-Dist: pyautogui
Requires-Dist: geopy
Dynamic: license-file
